{
  "Name": "EDA-methane-madrid",
  "Title": "Madrid Spain",
  "Themes": [
    "carbon-accounting"
  ],
  "Tags": [
    "Methane Emissions Analysis"
  ],
  "Description": "Time series of the column of excess methane over the \"Planta de biometanización y compostaje de Pinto\". The vertical dot-dashed lines correspond to detected methane plumes from the EMIT satellite.",
  "Resources": [
    {
      "Name": "Collection-only",
      "EndPoint": "Collection-only",
      "OverwriteBBox": [
        -3.67,
        40.23,
        -3.6100000000000003,
        40.29
      ]
    }
  ],
  "Agency": [
    "ESA"
  ]
}